snguess/__init__.py
snguess/data.py
snguess-0.1.4.dist-info/LICENSE
snguess-0.1.4.dist-info/METADATA
snguess-0.1.4.dist-info/WHEEL
snguess-0.1.4.dist-info/top_level.txt
snguess-0.1.4.dist-info/RECORD
