Metadata-Version: 2.1
Name: snguess
Version: 0.1.4
Summary: SNGuess
Home-page: https://github.com/nmiranda/SNGuess
Author: nmiranda
Author-email: nicolas.miranda@hu-berlin.de
Classifier: Programming Language :: Python :: 3
Classifier: License :: OSI Approved :: BSD License
Classifier: Operating System :: OS Independent
Requires-Python: >=3.10
License-File: LICENSE
Requires-Dist: ampel-hu-astro (>=0.8.3a1)
Requires-Dist: ampel-ztf (>=0.8.3a2)
Requires-Dist: scikit-learn
Requires-Dist: xgboost
Requires-Dist: pandas
Requires-Dist: numpy
Requires-Dist: astropy
Requires-Dist: seaborn
Requires-Dist: ipykernel
Requires-Dist: notebook
Provides-Extra: dev
Requires-Dist: build ; extra == 'dev'
Requires-Dist: twine ; extra == 'dev'
